langops/__init__.py
langops/alert/__init__.py
langops/alert/registry.py
langops/core/__init__.py
langops/core/base_alert.py
langops/core/base_llm.py
langops/core/base_parser.py
langops/core/base_prompt.py
langops/core/constants.py
langops/core/types.py
langops/llm/__init__.py
langops/llm/openai_llm.py
langops/llm/registry.py
langops/parser/__init__.py
langops/parser/error_parser.py
langops/parser/jenkins_parser.py
langops/parser/jenkins_patterns.py
langops/parser/registry.py
langops/prompt/__init__.py
langops/prompt/jenkins_error_prompt.py
langops/prompt/registry.py
langops-0.2.0.dist-info/LICENSE
langops-0.2.0.dist-info/METADATA
langops-0.2.0.dist-info/WHEEL
langops-0.2.0.dist-info/RECORD
