Metadata-Version: 2.3
Name: langops
Version: 0.2.0
Summary: LangOps is a modular SDK for parsing and analyzing CI/CD logs using AI. It provides a registry-based parser framework, LLM-ready JSON output, and plug-and-play pattern sets for tools like Jenkins, Docker, Sonar, JFrog, and more.
License: MIT
Author: Adi Roth
Author-email: adi.build.balance@gmail.com
Requires-Python: >=3.9
Classifier: License :: OSI Approved :: MIT License
Classifier: Programming Language :: Python :: 3
Classifier: Programming Language :: Python :: 3.9
Classifier: Programming Language :: Python :: 3.10
Classifier: Programming Language :: Python :: 3.11
Classifier: Programming Language :: Python :: 3.12
Classifier: Programming Language :: Python :: 3.13
Requires-Dist: coverage (>=7.0.0,<8.0.0)
Requires-Dist: openai (>=1.0.0,<2.0.0)
Requires-Dist: python-dotenv (>=1.0.0,<2.0.0)
Project-URL: Documentation, https://github.com/adirothbuilds/langops#readme
Project-URL: Homepage, https://github.com/adirothbuilds/langops
Project-URL: Repository, https://github.com/adirothbuilds/langops
